dbt_run_api/__init__.py
dbt_run_api-0.2.2.dist-info/licenses/LICENSE
dbt_run_api-0.2.2.dist-info/METADATA
dbt_run_api-0.2.2.dist-info/WHEEL
dbt_run_api-0.2.2.dist-info/top_level.txt
dbt_run_api-0.2.2.dist-info/RECORD
