Metadata-Version: 2.4
Name: dbt-run-api
Version: 0.2.2
Summary: A small package
Author-email: Matthias Leinweber <m.leinweber@datatactics.de>
Classifier: Programming Language :: Python :: 3
Classifier: License :: OSI Approved :: MIT License
Classifier: Operating System :: OS Independent
Requires-Python: >=3.8
License-File: LICENSE
Requires-Dist: dbt-core
Requires-Dist: uvicorn
Requires-Dist: fastapi
Requires-Dist: dbt-postgres
Requires-Dist: pytest
Requires-Dist: build
Requires-Dist: odd-cli
Requires-Dist: prometheus_client
Dynamic: license-file
